jarn.mkrelease-5.3-py3.11-nspkg.pth
jarn/mkrelease/__init__.py
jarn/mkrelease/__main__.py
jarn/mkrelease/chdir.py
jarn/mkrelease/colors.py
jarn/mkrelease/configparser.py
jarn/mkrelease/exit.py
jarn/mkrelease/mkrelease.py
jarn/mkrelease/process.py
jarn/mkrelease/python.py
jarn/mkrelease/scm.py
jarn/mkrelease/scp.py
jarn/mkrelease/setup.py
jarn/mkrelease/setuptools.py
jarn/mkrelease/tee.py
jarn/mkrelease/testing.py
jarn/mkrelease/twine.py
jarn/mkrelease/urlparser.py
jarn/mkrelease/utils.py
jarn.mkrelease-5.3.dist-info/LICENSE
jarn.mkrelease-5.3.dist-info/METADATA
jarn.mkrelease-5.3.dist-info/WHEEL
jarn.mkrelease-5.3.dist-info/entry_points.txt
jarn.mkrelease-5.3.dist-info/namespace_packages.txt
jarn.mkrelease-5.3.dist-info/top_level.txt
jarn.mkrelease-5.3.dist-info/RECORD
