Metadata-Version: 2.1
Name: jarn.mkrelease
Version: 5.3
Summary: Python package releaser
Home-page: https://github.com/Jarn/jarn.mkrelease
Author: Stefan H. Holek
Author-email: stefan@epy.co.at
License: BSD-2-Clause
Keywords: create,release,upload,python,sdist,sdists,wheel,wheels,pypi,releaser,package,packages,publish
Classifier: Development Status :: 5 - Production/Stable
Classifier: Environment :: Console
Classifier: Intended Audience :: Developers
Classifier: License :: OSI Approved :: BSD License
Classifier: Operating System :: MacOS :: MacOS X
Classifier: Operating System :: POSIX
Classifier: Programming Language :: Python :: 2
Classifier: Programming Language :: Python :: 3
Requires-Python: !=3.0.*,!=3.1.*,!=3.2.*,!=3.3.*,>=2.7
License-File: LICENSE
Requires-Dist: setuptools
Requires-Dist: lazy
Requires-Dist: wheel
Requires-Dist: blessed
Provides-Extra: filefinder
Requires-Dist: setuptools-subversion >=3.1 ; extra == 'filefinder'
Requires-Dist: setuptools-hg >=0.4 ; extra == 'filefinder'
Requires-Dist: setuptools-git >=1.2 ; extra == 'filefinder'
Provides-Extra: testing
Requires-Dist: nose2 ; extra == 'testing'
Requires-Dist: nose2-kflag ; extra == 'testing'
Provides-Extra: twine
Requires-Dist: twine ; extra == 'twine'
